spokeo/__init__.py
spokeo/main.py
spokeo-0.1.1.dist-info/METADATA
spokeo-0.1.1.dist-info/WHEEL
spokeo-0.1.1.dist-info/top_level.txt
spokeo-0.1.1.dist-info/RECORD
