Metadata-Version: 2.4
Name: spokeo
Version: 0.1.1
Summary: official API wrapper for Spokeo lookup service
Author: Wei Zhang
Author-email: zhangwei.dev@protonmail.com
Requires-Python: >=3.6
Requires-Dist: requests
Dynamic: author
Dynamic: author-email
Dynamic: description
Dynamic: description-content-type
Dynamic: requires-dist
Dynamic: requires-python
Dynamic: summary
